{
  "frames": {
    "card-0": {"x": 0, "y": 0, "w": 300, "h": 400},
    "card-1": {"x": 300, "y": 0, "w": 300, "h": 400},
    "card-2": {"x": 600, "y": 0, "w": 300, "h": 400},
    "card-3": {"x": 900, "y": 0, "w": 300, "h": 400},
    "card-4": {"x": 1200, "y": 0, "w": 300, "h": 400},
    "card-5": {"x": 1500, "y": 0, "w": 300, "h": 400},
    "card-6": {"x": 0, "y": 400, "w": 300, "h": 400},
    "card-7": {"x": 300, "y": 400, "w": 300, "h": 400},
    "card-8": {"x": 600, "y": 400, "w": 300, "h": 400},
    "card-9": {"x": 900, "y": 400, "w": 300, "h": 400},
    "card-10": {"x": 1200, "y": 400, "w": 300, "h": 400},
    "card-11": {"x": 1500, "y": 400, "w": 300, "h": 400},
    "card-12": {"x": 0, "y": 800, "w": 300, "h": 400},
    "card-13": {"x": 300, "y": 800, "w": 300, "h": 400},
    "card-14": {"x": 600, "y": 800, "w": 300, "h": 400},
    "card-15": {"x": 900, "y": 800, "w": 300, "h": 400},
    "card-16": {"x": 1200, "y": 800, "w": 300, "h": 400},
    "card-17": {"x": 1500, "y": 800, "w": 300, "h": 400},
    "card-18": {"x": 0, "y": 1200, "w": 300, "h": 400},
    "card-19": {"x": 300, "y": 1200, "w": 300, "h": 400},
    "card-20": {"x": 600, "y": 1200, "w": 300, "h": 400},
    "card-21": {"x": 900, "y": 1200, "w": 300, "h": 400}
  },
  "meta": {
    "app": "tarot-atlas",
    "version": "1.0",
    "image": "Tarot.png",
    "format": "RGBA8888",
    "size": {"w": 3300, "h": 800},
    "scale": "1"
  }
}

